asm2cfg/__init__.py
asm2cfg/__main__.py
asm2cfg/asm2cfg.py
asm2cfg/command_line.py
asm2cfg-0.2.2.data/scripts/gdb_asm2cfg.py
asm2cfg-0.2.2.dist-info/LICENSE
asm2cfg-0.2.2.dist-info/METADATA
asm2cfg-0.2.2.dist-info/WHEEL
asm2cfg-0.2.2.dist-info/entry_points.txt
asm2cfg-0.2.2.dist-info/top_level.txt
asm2cfg-0.2.2.dist-info/RECORD
