Metadata-Version: 2.1
Name: asm2cfg
Version: 0.2.2
Summary: Python command-line tool and GDB extension to view and save x86, ARM and objdump assembly files as control-flow graph (CFG) pdf files.
Home-page: https://github.com/Kazhuu/asm2cfg
Author: Mauri Mustonen
Author-email: kazooiebombchu@gmail.com
Project-URL: Bug Tracker, https://github.com/Kazhuu/asm2cfg/issues
Classifier: Programming Language :: Python :: 3
Classifier: License :: OSI Approved :: MIT License
Classifier: Operating System :: OS Independent
Requires-Python: >=3.6
License-File: LICENSE
Requires-Dist: graphviz (>=0.16)
